README.rst
setup.cfg
setup.py
pyjavaprops/__init__.py
pyjavaprops/javaproperties.py
pyjavaprops.egg-info/PKG-INFO
pyjavaprops.egg-info/SOURCES.txt
pyjavaprops.egg-info/dependency_links.txt
pyjavaprops.egg-info/entry_points.txt
pyjavaprops.egg-info/top_level.txt
pyjavaprops/settings/__init__.py
pyjavaprops/settings/base.py
pyjavaprops/settings/test.py
tests/__init__.py
tests/test_javaproperties.py