Metadata-Version: 1.1
Name: pyjavaprops
Version: 1.0.1
Summary: Tool to parse Java style properties file
Home-page: https://github.com/luiscberrocal/pyjavaprops
Author: Luis Carlos Berrocal
Author-email: luis.berrocal.1942@gmail.com
License: MIT
Download-URL: https://github.com/luiscberrocal/pyjavaprops/archive/v1.0.1.zip
Platform: UNKNOWN
Classifier: Development Status :: 4 - Beta
Classifier: Environment :: Console
Classifier: Intended Audience :: Developers
Classifier: License :: OSI Approved :: MIT License
Classifier: Operating System :: OS Independent
Classifier: Programming Language :: Python :: 3.4
Classifier: Topic :: Software Development :: Libraries
Classifier: Topic :: Software Development :: User Interfaces
Classifier: Topic :: Terminals
